AUTHORS
CHANGELOG
CONTRIBUTING.rst
INSTALL
LICENSE
MANIFEST.in
README.rst
VERSION
gpl-2.0.txt
setup.cfg
setup.py
odooselenium/__init__.py
odooselenium/__init__.pyc
odooselenium/api.py
odooselenium/api.pyc
odooselenium/test.py
odooselenium/test.pyc
odooselenium/ui.py
odooselenium/ui.pyc
odooselenium/wait.py
odooselenium/wait.pyc
odooselenium.egg-info/PKG-INFO
odooselenium.egg-info/SOURCES.txt
odooselenium.egg-info/dependency_links.txt
odooselenium.egg-info/not-zip-safe
odooselenium.egg-info/requires.txt
odooselenium.egg-info/top_level.txt
odooselenium/__pycache__/api.cpython-27-PYTEST.pyc
odooselenium/__pycache__/test.cpython-27-PYTEST.pyc
odooselenium/__pycache__/ui.cpython-27-PYTEST.pyc
odooselenium/__pycache__/wait.cpython-27-PYTEST.pyc