Metadata-Version: 1.1
Name: odooselenium
Version: 1.0.3
Summary: Tools to interact with Odoo using Selenium
Home-page: https://pypi.python.org/pypi/odooselenium
Author: Meta IT
Author-email: technique@meta-it.fr
License: GPLv2
Keywords: odoo selenium==2.53.0
Platform: UNKNOWN
Classifier: Development Status :: 1 - Planning
Classifier: License :: OSI Approved :: GNU General Public License v2 (GPLv2)
Classifier: Intended Audience :: Developers
Classifier: Programming Language :: Python :: 2.7
